README.md
setup.py
price_search_results_scraper/__init__.py
price_search_results_scraper.egg-info/PKG-INFO
price_search_results_scraper.egg-info/SOURCES.txt
price_search_results_scraper.egg-info/dependency_links.txt
price_search_results_scraper.egg-info/requires.txt
price_search_results_scraper.egg-info/top_level.txt